azure/mgmt/hybridconnectivity/__init__.py
azure/mgmt/hybridconnectivity/_configuration.py
azure/mgmt/hybridconnectivity/_hybrid_connectivity_mgmt_client.py
azure/mgmt/hybridconnectivity/_patch.py
azure/mgmt/hybridconnectivity/_serialization.py
azure/mgmt/hybridconnectivity/_vendor.py
azure/mgmt/hybridconnectivity/_version.py
azure/mgmt/hybridconnectivity/py.typed
azure/mgmt/hybridconnectivity/aio/__init__.py
azure/mgmt/hybridconnectivity/aio/_configuration.py
azure/mgmt/hybridconnectivity/aio/_hybrid_connectivity_mgmt_client.py
azure/mgmt/hybridconnectivity/aio/_patch.py
azure/mgmt/hybridconnectivity/aio/operations/__init__.py
azure/mgmt/hybridconnectivity/aio/operations/_endpoints_operations.py
azure/mgmt/hybridconnectivity/aio/operations/_operations.py
azure/mgmt/hybridconnectivity/aio/operations/_patch.py
azure/mgmt/hybridconnectivity/aio/operations/_service_configurations_operations.py
azure/mgmt/hybridconnectivity/models/__init__.py
azure/mgmt/hybridconnectivity/models/_hybrid_connectivity_mgmt_client_enums.py
azure/mgmt/hybridconnectivity/models/_models_py3.py
azure/mgmt/hybridconnectivity/models/_patch.py
azure/mgmt/hybridconnectivity/operations/__init__.py
azure/mgmt/hybridconnectivity/operations/_endpoints_operations.py
azure/mgmt/hybridconnectivity/operations/_operations.py
azure/mgmt/hybridconnectivity/operations/_patch.py
azure/mgmt/hybridconnectivity/operations/_service_configurations_operations.py
azure_mgmt_hybridconnectivity-1.0.0.dist-info/LICENSE
azure_mgmt_hybridconnectivity-1.0.0.dist-info/METADATA
azure_mgmt_hybridconnectivity-1.0.0.dist-info/WHEEL
azure_mgmt_hybridconnectivity-1.0.0.dist-info/top_level.txt
azure_mgmt_hybridconnectivity-1.0.0.dist-info/RECORD
